{
  "title": "Z1 - Frigid River C",
  "sections": {
    "Description (verbatim)": "The river descends here into a valley.\nThere is a narrow beach on the west shore below the cliffs. In the distance a faint rumbling can be heard.\nThe magic boat contains:\n\tA tan label.",
    "Exits (as reported)": [
      "W → [[Z1 - White Cliffs Beach]]",
      "WAIT → [[Z1 - Frigid River D]]"
    ],
    "Blocked movements": [
      "(none)"
    ],
    "Hidden/conditional transitions": [
      "..."
    ],
    "Objects present": [
      "..."
    ],
    "Hazards/NPCs": [
      "..."
    ],
    "Key parser interactions": [
      "WAIT"
    ],
    "State notes": [
      "Lit"
    ],
    "Mapping notes": {
      "Internal ID": "Z1-R-066",
      "First mapped": "2026 Feb. 10",
      "Revisions": ""
    }
  }
}
